slowedreverb/__init__.py
slowedreverb/slowedreverb.py
slowedreverb-0.0.1.dist-info/METADATA
slowedreverb-0.0.1.dist-info/WHEEL
slowedreverb-0.0.1.dist-info/top_level.txt
slowedreverb-0.0.1.dist-info/RECORD
