Metadata-Version: 2.1
Name: slowedreverb
Version: 0.0.1
Summary: A basic python script to make slowed + reverbs.
Home-page: UNKNOWN
Author: JustCow
Author-email: <justcow@pm.me>
License: UNKNOWN
Keywords: python,music,slowed reverb,justcow
Platform: UNKNOWN
Classifier: Programming Language :: Python :: 3
Classifier: Operating System :: Unix
Classifier: Operating System :: MacOS :: MacOS X
Classifier: Operating System :: Microsoft :: Windows
Requires-Dist: pedalboard
